LICENSE.txt
MANIFEST.in
README.md
setup.py
Mynus.egg-info/PKG-INFO
Mynus.egg-info/SOURCES.txt
Mynus.egg-info/dependency_links.txt
Mynus.egg-info/top_level.txt
bin/mynus
mynus/__init__.py
mynus/mynus.py
mynus/utils.py
mynus/templates/new.html
mynus/templates/page.html
mynus/templates/pages.html