Metadata-Version: 1.0
Name: Mynus
Version: 0.1.0
Summary: A minimalist and pure python wiki with no dependencies.
Home-page: http://pypi.python.org/pypi/Mynus
Author: Romain Gauthier
Author-email: romain.gauthier@masteri2l.org
License: GNU Affero General Public License v3 or later
Platform: UNKNOWN
Classifier: Development Status :: 3 - Alpha
Classifier: License :: OSI Approved :: GNU Affero General Public License v3
Classifier: Operating System :: OS Independent
Classifier: Programming Language :: Python :: 2.6
Classifier: Topic :: Utilities
